<?xml version="1.0" encoding="UTF-8"?><labels locale="de">
<label key="key:620756997:110020100" value="Orksippe"/>
<label key="key:620756997:171490420" value="Kreatur"/>
<label key="key:620756997:171695190" value="Zwerg"/>
<label key="key:620756997:171832452" value="Riesensippe"/>
<label key="key:620756997:171952046" value="Mensch"/>
<label key="key:620756997:172724988" value="Trollsippe"/>
<label key="key:620756997:228830004" value="Die Toten"/>
<label key="key:620756997:28510594" value="Placeholder"/>
<label key="key:620756997:39879132" value="Uralte böse Macht"/>
<label key="key:620756997:62403070" value="Drachensippe"/>
<label key="key:620756997:66438820" value="Hobbit"/>
<label key="key:620756997:67491332" value="Spinnen und Insekten"/>
<label key="key:620756997:71889189" value="Kreaturen der Natur"/>
<label key="key:620756997:72959492" value="Objekt"/>
<label key="key:620756997:80037141" value="Einzigartig"/>
<label key="key:620756997:80074270" value="Unsichtbar"/>
<label key="key:620756997:81411110" value="Elb"/>
</labels>
