<?xml version="1.0" encoding="UTF-8"?><labels locale="de">
<label key="key:620757493:105359509" value="Scharm체tzelheldentum"/>
<label key="key:620757493:110607011" value="Zeichen"/>
<label key="key:620757493:112938686" value="Schadensred. gegen Westernis."/>
<label key="key:620757493:113212494" value="Schadensred. gegen Blitze."/>
<label key="key:620757493:116340771" value="Bonus: Schaden"/>
<label key="key:620757493:14565486" value="Schadensred. gegen Beleriand."/>
<label key="key:620757493:151559154" value="Abnutzung"/>
<label key="key:620757493:163739256" value="St채rke"/>
<label key="key:620757493:166524009" value="Erholung"/>
<label key="key:620757493:171758446" value="Schadensreduzierung gegen Licht"/>
<label key="key:620757493:171942949" value="Hoffnung"/>
<label key="key:620757493:176664046" value="Schadensreduzierung gegen Schatten"/>
<label key="key:620757493:219367397" value="R체stung"/>
<label key="key:620757493:242642800" value="Verbesserte EP"/>
<label key="key:620757493:245493191" value="Laufgeschwindigkeit"/>
<label key="key:620757493:250830894" value="Schadensred. gegen uralt. Zwerg."/>
<label key="key:620757493:258278878" value="Schadensreduzierung gegen Frost"/>
<label key="key:620757493:261525113" value="Monsterspielschub"/>
<label key="key:620757493:266258039" value="Heilen"/>
<label key="key:620757493:266973180" value="Wiederbelebung"/>
<label key="key:620757493:267321413" value="Moral"/>
<label key="key:620757493:59406580" value="Erfahrungsbonus"/>
<label key="key:620757493:59497154" value="Kraft"/>
<label key="key:620757493:61260958" value="Entschlossenheit"/>
<label key="key:620757493:63534302" value="Schadensreduzierung gegen Feuer"/>
<label key="key:620757493:77168718" value="Schadensreduzierung gegen S채ure"/>
<label key="key:620757493:7932048" value="Gegenstands-Erfahrungsbonus"/>
<label key="key:620757493:84361806" value="Entfernung von Furcht"/>
</labels>
