<?xml version="1.0" encoding="UTF-8"?><labels locale="en">
<label key="key:620899295:113435837" value="Medium"/>
<label key="key:620899295:116503630" value="Champion"/>
<label key="key:620899295:130340707" value="Helm's Deep"/>
<label key="key:620899295:147809548" value="Minstrel"/>
<label key="key:620899295:16883458" value="Brawler"/>
<label key="key:620899295:17758782" value="Captain"/>
<label key="key:620899295:189800302" value="Warden"/>
<label key="key:620899295:208981778" value="Hunter"/>
<label key="key:620899295:21077826" value="Burglar"/>
<label key="key:620899295:254051150" value="Class Specialization"/>
<label key="key:620899295:264294930" value="Runekeeper"/>
<label key="key:620899295:266671314" value="Lore-master"/>
<label key="key:620899295:48286658" value="Mariner"/>
<label key="key:620899295:52261662" value="Guardian"/>
<label key="key:620899295:5320601" value="Heavy"/>
<label key="key:620899295:7170740" value="Light"/>
<label key="key:620899295:83792967" value="Beorning"/>
</labels>
