<?xml version="1.0" encoding="UTF-8"?><skirmishTraits>
<trait identifier="1879156209" name="Role: Protector"/>
<trait identifier="1879156207" name="Role: Archer"/>
<trait identifier="1879156206" name="Role: Warrior"/>
<trait identifier="1879156204" name="Role: Bannerguard"/>
<trait identifier="1879156205" name="Role: Herbalist"/>
<trait identifier="1879156208" name="Role: Sage"/>
<trait identifier="1879154339" name="Light Armour Training"/>
<trait identifier="1879154340" name="Medium Armour Training"/>
<trait identifier="1879154338" name="Heavy Armour Training"/>
<trait identifier="1879154341" name="Shield Training"/>
<trait identifier="1879154343" name="Parry Training"/>
<trait identifier="1879154342" name="Evasion Training"/>
<trait identifier="1879156199" name="Defensive Training"/>
<trait identifier="1879156203" name="Strength of Resolve"/>
<trait identifier="1879154345" name="Practised Critical"/>
<trait identifier="1879154352" name="Resurgent Morale"/>
<trait identifier="1879154353" name="Resurgent Power"/>
<trait identifier="1879154358" name="Boundless Morale"/>
<trait identifier="1879154359" name="Boundless Power"/>
<trait identifier="1879156240" name="Boundless Resolve"/>
<trait identifier="1879156227" name="Taunting Strike"/>
<trait identifier="1879156226" name="Self-reliance"/>
<trait identifier="1879156225" name="Threatening Riposte"/>
<trait identifier="1879156217" name="Quick Sweep"/>
<trait identifier="1879156216" name="Strong Sweep"/>
<trait identifier="1879156218" name="Forceful Strike"/>
<trait identifier="1879156221" name="Pinpoint Shot"/>
<trait identifier="1879156219" name="Deadly Shot"/>
<trait identifier="1879156212" name="Inspired Retaliation"/>
<trait identifier="1879156211" name="Cry of the Enduring"/>
<trait identifier="1879156224" name="Word of Battle"/>
<trait identifier="1879156222" name="Chilling Winds"/>
<trait identifier="1879156214" name="Refreshing Herbs"/>
<trait identifier="1879156213" name="Nature's Cure"/>
<trait identifier="1879156215" name="Nature's Power"/>
<trait identifier="1879156238" name="Ultimate: Defender of All"/>
<trait identifier="1879156239" name="Ultimate: Solitary Defender"/>
<trait identifier="1879156233" name="Ultimate: Berserker"/>
<trait identifier="1879156232" name="Ultimate: Blood-seeker"/>
<trait identifier="1879156235" name="Ultimate: Bold Arrow"/>
<trait identifier="1879156234" name="Ultimate: Wound-seeker"/>
<trait identifier="1879156229" name="Ultimate: Banner of Precision"/>
<trait identifier="1879156228" name="Ultimate: Banner of Protection"/>
<trait identifier="1879156236" name="Ultimate: Word of Flame"/>
<trait identifier="1879156237" name="Ultimate: Word of Frost"/>
<trait identifier="1879156230" name="Ultimate: Words of Healing"/>
<trait identifier="1879156231" name="Ultimate: Words of Power"/>
<trait identifier="1879162936" name="Summon the Foe"/>
<trait identifier="1879162937" name="Potent Strike"/>
<trait identifier="1879162938" name="Inspiring Shout"/>
<trait identifier="1879162939" name="Bold Strike"/>
<trait identifier="1879162940" name="Salve of Resolve"/>
<trait identifier="1879162941" name="Herbs of Boundless Endurance"/>
<trait identifier="1879162942" name="Strengthening Draught"/>
<trait identifier="1879162943" name="Disarming Strikes"/>
<trait identifier="1879162944" name="Whirling Wounds"/>
<trait identifier="1879162945" name="Carving Strike"/>
<trait identifier="1879162946" name="Distracting Shot"/>
<trait identifier="1879162947" name="Marking Arrow"/>
<trait identifier="1879162948" name="Refocus"/>
<trait identifier="1879162949" name="Wounding Arrow"/>
<trait identifier="1879162950" name="Oil of the Dragon's Rage"/>
<trait identifier="1879162951" name="Weakening Draught"/>
<trait identifier="1879162952" name="Fire of the Wise"/>
<trait identifier="1879162953" name="Tanglefoot"/>
<trait identifier="1879162954" name="Threatening Shout"/>
<trait identifier="1879162955" name="Whirl of Fury"/>
<trait identifier="1879162956" name="Defender's Strike"/>
<trait identifier="1879162928" name="Resilient Body"/>
<trait identifier="1879162929" name="Physical Potency"/>
<trait identifier="1879162930" name="Physical Resilience"/>
<trait identifier="1879174646" name="Armour Penetration"/>
<trait identifier="1879162931" name="Battle-field Finesse"/>
<trait identifier="1879162957" name="Tactical Potency"/>
<trait identifier="1879162958" name="Tactical Resilience"/>
<trait identifier="1879174521" name="Armoured Assault"/>
<trait identifier="1879174522" name="Strong Block"/>
<trait identifier="1879174523" name="Defensive Warfare"/>
<trait identifier="1879174524" name="Battle-master"/>
<trait identifier="1879174527" name="Duck Aside"/>
<trait identifier="1879174528" name="Invigouration"/>
<trait identifier="1879174530" name="Lead the Way"/>
<trait identifier="1879174532" name="Tactical Artistry"/>
<trait identifier="1879174533" name="Swift Parry"/>
<trait identifier="1879174548" name="Piercing Might"/>
<trait identifier="1879174534" name="Defender's Bane"/>
<trait identifier="1879174537" name="Strong Resistances"/>
<trait identifier="1879174539" name="Fancy Footwork"/>
<trait identifier="1879174541" name="Strong of Will"/>
<trait identifier="1879179476" name="Race: Dwarf-kind"/>
<trait identifier="1879179473" name="Race: Elf-maiden"/>
<trait identifier="1879179472" name="Race: Elf-sire"/>
<trait identifier="1879179475" name="Race: Hobbit-lass"/>
<trait identifier="1879179474" name="Race: Hobbit-lad"/>
<trait identifier="1879179471" name="Race: Woman"/>
<trait identifier="1879179470" name="Race: Man"/>
<trait identifier="1879239341" name="Race: Rohirrim Male"/>
<trait identifier="1879239340" name="Race: Rohirrim Female"/>
<trait identifier="1879173800" name="Hair Colour: Red"/>
<trait identifier="1879173738" name="Hair Colour: White"/>
<trait identifier="1879173762" name="Hair Colour: Black"/>
<trait identifier="1879173866" name="Hair Colour: Blonde"/>
<trait identifier="1879173929" name="Hair Colour: White"/>
<trait identifier="1879173869" name="Hair Colour: Blonde"/>
<trait identifier="1879173735" name="Hair Colour: Red"/>
<trait identifier="1879173893" name="Hair Colour: Black"/>
<trait identifier="1879173884" name="Hair Colour: White"/>
<trait identifier="1879173821" name="Hair Colour: Blonde"/>
<trait identifier="1879173864" name="Hair Colour: Red"/>
<trait identifier="1879173793" name="Hair Colour: Black"/>
<trait identifier="1879173750" name="Hair Colour: White"/>
<trait identifier="1879173763" name="Hair Colour: Blonde"/>
<trait identifier="1879173754" name="Hair Colour: Red"/>
<trait identifier="1879173725" name="Hair Colour: Black"/>
<trait identifier="1879173924" name="Hair Colour: White"/>
<trait identifier="1879173774" name="Hair Colour: Blonde"/>
<trait identifier="1879173769" name="Hair Colour: Red"/>
<trait identifier="1879173764" name="Hair Colour: Black"/>
<trait identifier="1879173820" name="Hair Colour: White"/>
<trait identifier="1879173870" name="Hair Colour: Blonde"/>
<trait identifier="1879173716" name="Hair Colour: Red"/>
<trait identifier="1879173848" name="Hair Colour: Black"/>
<trait identifier="1879173868" name="Hair Colour: White"/>
<trait identifier="1879173804" name="Hair Colour: Blonde"/>
<trait identifier="1879173904" name="Hair Colour: Red"/>
<trait identifier="1879173916" name="Hair Colour: Black"/>
<trait identifier="1879173858" name="Short Hair - Thin Beard"/>
<trait identifier="1879173926" name="Thinning Hair - Full Beard"/>
<trait identifier="1879173812" name="Short Hair - Thonged Beard"/>
<trait identifier="1879173726" name="Long Hair - Thick Beard"/>
<trait identifier="1879173813" name="Short Hair - Goatee"/>
<trait identifier="1879173833" name="Long Hair - Beard"/>
<trait identifier="1879173784" name="Long Hair - Clean Shaven"/>
<trait identifier="1879173879" name="Short Hair - Handlebar"/>
<trait identifier="1879173780" name="Medium Hair - Tight Bun"/>
<trait identifier="1879173876" name="Medium Hair - Fancy Braid"/>
<trait identifier="1879173881" name="Medium Hair - Fringe"/>
<trait identifier="1879173781" name="Short Hair - Bowl Cut"/>
<trait identifier="1879173747" name="Medium Hair - Flip Cut"/>
<trait identifier="1879173761" name="Short Hair - Fringe"/>
<trait identifier="1879173810" name="Medium Hair - Tight Bun"/>
<trait identifier="1879173877" name="Long Hair - Pulled Back"/>
<trait identifier="1879173901" name="Medium Hair - Pigtails"/>
<trait identifier="1879173834" name="Long Hair - Wood-elf Warrior"/>
<trait identifier="1879173920" name="Long Hair - Straight Cut"/>
<trait identifier="1879173787" name="Long Hair - Fringe Over Eye"/>
<trait identifier="1879173909" name="Long Hair - Ponytail"/>
<trait identifier="1879173894" name="Long Hair - Left Part"/>
<trait identifier="1879173832" name="Long Hair - Right Part"/>
<trait identifier="1879173849" name="Short Hair - Left Part"/>
<trait identifier="1879173891" name="Short hair - Fringe"/>
<trait identifier="1879176775" name="Fancy Green Commoner Outift"/>
<trait identifier="1879176779" name="Red Commoner Outfit"/>
<trait identifier="1879176780" name="Fancy Blue Outfit"/>
<trait identifier="1879176783" name="Chain Guard Outfit"/>
<trait identifier="1879176784" name="Leather Guard Outfit"/>
<trait identifier="1879176786" name="Scale Guard Outfit"/>
<trait identifier="1879176788" name="Dress and Coat"/>
<trait identifier="1879176789" name="Dwarf-surcoat"/>
<trait identifier="1879176807" name="Elven Surcoat"/>
<trait identifier="1879176825" name="Hobbit-surcoat"/>
<trait identifier="1879176843" name="Man-surcoat"/>
<trait identifier="1879176862" name="Black and Red Riding Outfit"/>
<trait identifier="1879176865" name="Gold Smoker's Outfit"/>
<trait identifier="1879176867" name="Beige Formalwear"/>
<trait identifier="1879176871" name="Blue Worker Outfit"/>
<trait identifier="1879176873" name="Navy Mayor's Outfit"/>
<trait identifier="1879176878" name="Purple Mayor's Outfit"/>
<trait identifier="1879176879" name="Green Suitcoat"/>
<trait identifier="1879176881" name="Chain Guard Outfit"/>
<trait identifier="1879176882" name="Leather Guard Outfit"/>
<trait identifier="1879176884" name="Scale Guard Outfit"/>
<trait identifier="1879176887" name="Dwarf-surcoat"/>
<trait identifier="1879176905" name="Elven Surcoat"/>
<trait identifier="1879176923" name="Hobbit-surcoat"/>
<trait identifier="1879176960" name="Beige Farmer's Outfit"/>
<trait identifier="1879176964" name="Gold Patron Outfit"/>
<trait identifier="1879176726" name="Red Formalwear"/>
<trait identifier="1879176967" name="Dark Beggars' Garb"/>
<trait identifier="1879176731" name="Red Burglar Garb"/>
<trait identifier="1879176969" name="Chain Guard Outfit"/>
<trait identifier="1879176970" name="Leather Guard Outfit"/>
<trait identifier="1879176972" name="Scale Guard Outfit"/>
<trait identifier="1879176975" name="Dwarf-surcoat"/>
<trait identifier="1879176993" name="Elven Surcoat"/>
<trait identifier="1879177011" name="Hobbit-surcoat"/>
<trait identifier="1879177029" name="Man-surcoat"/>
<trait identifier="1879177033" name="Blue Formalwear"/>
<trait identifier="1879177037" name="Green Merchant's Outfit"/>
<trait identifier="1879177039" name="Blue Goodwife's Outfit"/>
<trait identifier="1879177044" name="Red Dress"/>
<trait identifier="1879177047" name="Red Burglar Garb"/>
<trait identifier="1879177048" name="Chain Guard Outfit"/>
<trait identifier="1879177049" name="Leather Guard Outfit"/>
<trait identifier="1879177051" name="Scale Guard Outfit"/>
<trait identifier="1879177053" name="Dwarf-surcoat"/>
<trait identifier="1879177071" name="Elven Surcoat"/>
<trait identifier="1879177089" name="Hobbit-surcoat"/>
<trait identifier="1879177107" name="Man-surcoat"/>
<trait identifier="1879177125" name="Maiden's Dress"/>
<trait identifier="1879177126" name="Matron's Dress"/>
<trait identifier="1879177128" name="Green Robe"/>
<trait identifier="1879177129" name="Red Robe"/>
<trait identifier="1879177131" name="Chain Guard Outfit"/>
<trait identifier="1879177132" name="Leather Guard Outfit"/>
<trait identifier="1879177134" name="Scale Guard Outfit"/>
<trait identifier="1879177154" name="Elven Surcoat"/>
<trait identifier="1879177172" name="Hobbit-surcoat"/>
<trait identifier="1879177190" name="Man-surcoat"/>
<trait identifier="1879177288" name="Commoner's Outfit"/>
<trait identifier="1879177289" name="Blue Nobles' Garb"/>
<trait identifier="1879177291" name="Red Nobles' Garb"/>
<trait identifier="1879177293" name="Chain Guard Outfit"/>
<trait identifier="1879177294" name="Leather Guard Outfit"/>
<trait identifier="1879177296" name="Scale Guard Outfit"/>
<trait identifier="1879177299" name="Dwarf-surcoat"/>
<trait identifier="1879177317" name="Elven Surcoat"/>
<trait identifier="1879177335" name="Hobbit-surcoat"/>
<trait identifier="1879177353" name="Man-surcoat"/>
<trait identifier="1879177371" name="Commoner Outfit"/>
<trait identifier="1879177374" name="Merchant's Outfit"/>
<trait identifier="1879177378" name="Noble's Outfit"/>
<trait identifier="1879177381" name="Worker's Outfit"/>
<trait identifier="1879177384" name="Chain Guard Outfit"/>
<trait identifier="1879177385" name="Leather Guard Outfit"/>
<trait identifier="1879177387" name="Scale Guard Outfit"/>
<trait identifier="1879177390" name="Dwarf-surcoat"/>
<trait identifier="1879177408" name="Elven Surcoat"/>
<trait identifier="1879177426" name="Hobbit-surcoat"/>
<trait identifier="1879177444" name="Man-surcoat"/>
<trait identifier="1879239044" name="Appearance -  Male Rohan Warrior"/>
<trait identifier="1879239042" name="Appearance - Female Rohan Warrior"/>
<trait identifier="1879455576" name="Mírdan Warrior with Helmet"/>
<trait identifier="1879455573" name="Mírdan Warrior Outfit"/>
<trait identifier="1879455575" name="Mírdan Warrior with Helmet"/>
<trait identifier="1879455574" name="Mírdan Warrior Outfit"/>
</skirmishTraits>
