<?xml version="1.0" encoding="UTF-8"?><travelsMap>
<label text="key:620757473:147390958">
<uiPosition x="452" y="478" width="148" height="1"/>
</label>
<label text="key:620757473:196760524">
<uiPosition x="668" y="752" width="127" height="20"/>
</label>
<label text="key:620757473:77029652">
<uiPosition x="532" y="534" width="137" height="20"/>
</label>
<label text="key:620757473:61611854">
<uiPosition x="840" y="792" width="92" height="20"/>
</label>
<label text="key:620757473:45983523">
<uiPosition x="505" y="1018" width="160" height="20"/>
</label>
<label text="key:620757473:207272996">
<uiPosition x="618" y="836" width="129" height="36"/>
</label>
<label text="key:620757473:62041422">
<uiPosition x="889" y="852" width="92" height="20"/>
</label>
<label text="key:620757473:265125292">
<uiPosition x="805" y="952" width="116" height="47"/>
</label>
<label text="key:620757473:171341726">
<uiPosition x="928" y="122" width="150" height="20"/>
</label>
<label text="key:620757473:207476772">
<uiPosition x="991" y="926" width="92" height="58"/>
</label>
<label text="key:620757473:14108428">
<uiPosition x="228" y="391" width="92" height="20"/>
</label>
<label text="key:620757473:49595299">
<uiPosition x="1144" y="211" width="140" height="20"/>
</label>
<label text="key:620757473:158247900">
<uiPosition x="601" y="501" width="88" height="20"/>
</label>
<label text="key:620757473:134629970">
<uiPosition x="263" y="1059" width="180" height="30"/>
</label>
<label text="key:620757473:113873141">
<uiPosition x="295" y="374" width="200" height="20"/>
</label>
<label text="key:620757473:246923276">
<uiPosition x="294" y="315" width="92" height="20"/>
</label>
<label text="key:620757473:132904478">
<uiPosition x="926" y="730" width="140" height="20"/>
</label>
<label text="key:620757473:238884444">
<uiPosition x="410" y="239" width="103" height="20"/>
</label>
<label text="key:620757473:81323875">
<uiPosition x="950" y="690" width="140" height="20"/>
</label>
<label text="key:620757473:88504556">
<uiPosition x="356" y="460" width="92" height="26"/>
</label>
<label text="key:620757473:124643045">
<uiPosition x="694" y="575" width="160" height="20"/>
</label>
<label text="key:620757473:71747778">
<uiPosition x="1114" y="752" width="140" height="20"/>
</label>
<label text="key:620757473:15110188">
<uiPosition x="450" y="396" width="140" height="20"/>
</label>
<label text="key:620757473:78066558">
<uiPosition x="856" y="299" width="160" height="20"/>
</label>
<label text="key:620757473:91697854">
<uiPosition x="897" y="380" width="140" height="20"/>
</label>
<label text="key:620757473:166994348">
<uiPosition x="605" y="262" width="92" height="20"/>
</label>
<label text="key:620757473:201841556">
<uiPosition x="676" y="70" width="160" height="20"/>
</label>
<label text="key:620757473:10643477">
<uiPosition x="1071" y="903" width="140" height="20"/>
</label>
<label text="key:620757473:124587228">
<uiPosition x="432" y="286" width="92" height="20"/>
</label>
<label text="key:620757473:206932484">
<uiPosition x="740" y="228" width="140" height="20"/>
</label>
<label text="key:620757473:104509548">
<uiPosition x="488" y="440" width="140" height="20"/>
</label>
<label text="key:620757473:20702533">
<uiPosition x="818" y="143" width="140" height="20"/>
</label>
<label text="key:620757473:208750252">
<uiPosition x="674" y="356" width="200" height="20"/>
</label>
<label text="key:620757473:250645822">
<uiPosition x="816" y="1272" width="123" height="20"/>
</label>
<label text="key:620757473:176935020">
<uiPosition x="574" y="396" width="161" height="20"/>
</label>
<label text="key:620757473:184347576">
<uiPosition x="928" y="250" width="150" height="20"/>
</label>
<label text="key:620757473:100139308">
<uiPosition x="1051" y="393" width="114" height="36"/>
</label>
<label text="key:620757473:199047059">
<uiPosition x="644" y="1134" width="177" height="20"/>
</label>
<label text="key:620757473:241624508">
<uiPosition x="884" y="469" width="113" height="20"/>
</label>
<label text="key:620757473:132845004">
<uiPosition x="506" y="600" width="121" height="20"/>
</label>
<label text="key:620757473:177558876">
<uiPosition x="716" y="460" width="123" height="20"/>
</label>
<label text="key:620757473:74482380">
<uiPosition x="878" y="549" width="109" height="20"/>
</label>
<label text="key:620757473:230762188">
<uiPosition x="514" y="653" width="92" height="20"/>
</label>
<label text="key:620757473:12188636">
<uiPosition x="913" y="626" width="92" height="20"/>
</label>
<node npcId="1879447471" tooltip="key:620774803:178999509">
<uiPosition x="327" y="386"/>
</node>
<node npcId="1879186736" tooltip="key:620774803:77097909">
<uiPosition x="634" y="585"/>
</node>
<node npcId="1879268514" tooltip="key:620906214:125289365">
<uiPosition x="813" y="570"/>
</node>
<node npcId="1879447469" tooltip="key:620774803:35232165">
<uiPosition x="323" y="405"/>
</node>
<node npcId="1879447477" tooltip="key:620774803:205201733">
<uiPosition x="345" y="363"/>
</node>
<node npcId="1879137217" tooltip="key:620774803:27046085">
<uiPosition x="749" y="481"/>
</node>
<node npcId="1879447479" tooltip="key:620774803:4692245">
<uiPosition x="358" y="385"/>
</node>
<node npcId="1879152989" tooltip="key:620774803:252779045">
<uiPosition x="771" y="498"/>
</node>
<node npcId="1879447475" tooltip="key:620774803:203390661">
<uiPosition x="345" y="397"/>
</node>
<node npcId="1879153001" tooltip="key:620774803:220427813">
<uiPosition x="788" y="484"/>
</node>
<node npcId="1879447473" tooltip="key:620774803:30488389">
<uiPosition x="341" y="413"/>
</node>
<node npcId="1879153222" tooltip="key:620774803:155745376">
<uiPosition x="799" y="495"/>
</node>
<node npcId="1879153000" capital="true" tooltip="key:620774803:171373765">
<uiPosition x="805" y="509"/>
</node>
<node npcId="1879153002" tooltip="key:620774803:29197957">
<uiPosition x="823" y="515"/>
</node>
<node npcId="1879158093" tooltip="key:620774803:114354085">
<uiPosition x="830" y="501"/>
</node>
<node npcId="1879158090" tooltip="key:620774803:41056053">
<uiPosition x="854" y="493"/>
</node>
<node npcId="1879158095" tooltip="key:620774803:77180389">
<uiPosition x="861" y="506"/>
</node>
<node npcId="1879158096" capital="true" tooltip="key:620774803:156013237">
<uiPosition x="876" y="494"/>
</node>
<node npcId="1879423258" tooltip="key:620774803:53589">
<uiPosition x="780" y="80"/>
</node>
<node npcId="1879173690" tooltip="key:620774803:13629685">
<uiPosition x="890" y="510"/>
</node>
<node npcId="1879470665" tooltip="key:620774803:165363029">
<uiPosition x="324" y="1139"/>
</node>
<node npcId="1879423259" tooltip="key:620774803:268181813">
<uiPosition x="790" y="108"/>
</node>
<node npcId="1879158092" tooltip="key:620774803:74972869">
<uiPosition x="898" y="488"/>
</node>
<node npcId="1879470768" tooltip="key:620774803:257613669">
<uiPosition x="295" y="1115"/>
</node>
<node npcId="1879423256" tooltip="key:620774803:167095669">
<uiPosition x="736" y="88"/>
</node>
<node npcId="1879173695" tooltip="key:620774803:20002197">
<uiPosition x="911" y="502"/>
</node>
<node npcId="1879474202" tooltip="key:620774803:256888133">
<uiPosition x="289" y="1098"/>
</node>
<node npcId="1879423257" tooltip="key:620774803:167206181">
<uiPosition x="756" y="116"/>
</node>
<node npcId="1879216508" tooltip="key:620774803:144732469">
<uiPosition x="606" y="627"/>
</node>
<node npcId="1879474470" tooltip="key:620774803:170886197">
<uiPosition x="274" y="1093"/>
</node>
<node npcId="1879423253" tooltip="key:620774803:82635621">
<uiPosition x="754" y="144"/>
</node>
<node npcId="1879216512" tooltip="key:620774803:46714453">
<uiPosition x="632" y="631"/>
</node>
<node npcId="1879474484" tooltip="key:620774803:77649493">
<uiPosition x="268" y="1075"/>
</node>
<node npcId="1879423254" tooltip="key:620774803:82320181">
<uiPosition x="780" y="158"/>
</node>
<node npcId="1879216498" capital="true" tooltip="key:620774803:41579781">
<uiPosition x="625" y="648"/>
</node>
<node npcId="1879470699" tooltip="key:620774803:225711909">
<uiPosition x="242" y="1068"/>
</node>
<node npcId="1879423255" tooltip="key:620774803:23319477">
<uiPosition x="782" y="122"/>
</node>
<node npcId="1879395403" tooltip="key:620774803:8825013">
<uiPosition x="1074" y="869"/>
</node>
<node npcId="1879216510" tooltip="key:620774803:193098261">
<uiPosition x="607" y="664"/>
</node>
<node npcId="1879474398" tooltip="key:620774803:17299589">
<uiPosition x="236" y="1088"/>
</node>
<node npcId="1879423252" tooltip="key:620774803:109316165">
<uiPosition x="760" y="162"/>
</node>
<node npcId="1879395405" tooltip="key:620774803:174458981">
<uiPosition x="1078" y="848"/>
</node>
<node npcId="1879216514" tooltip="key:620774803:181655621">
<uiPosition x="593" y="681"/>
</node>
<node npcId="1879474170" tooltip="key:620774803:201882901">
<uiPosition x="266" y="1140"/>
</node>
<node npcId="1879422326" tooltip="key:620774803:103785061">
<uiPosition x="776" y="112"/>
</node>
<node npcId="1879395404" tooltip="key:620774803:109270293">
<uiPosition x="1100" y="853"/>
</node>
<node npcId="1879216516" tooltip="key:620774803:255757253">
<uiPosition x="627" y="670"/>
</node>
<node npcId="1879475363" tooltip="key:620774803:59375765">
<uiPosition x="617" y="1125"/>
</node>
<node npcId="1879423288" tooltip="key:620774803:224244693">
<uiPosition x="740" y="174"/>
</node>
<node npcId="1879395402" tooltip="key:620774803:193621701">
<uiPosition x="1094" y="883"/>
</node>
<node npcId="1879216500" tooltip="key:620774803:41761317">
<uiPosition x="654" y="635"/>
</node>
<node npcId="1879475325" tooltip="key:620774803:231756245">
<uiPosition x="597" y="1116"/>
</node>
<node npcId="1879423249" tooltip="key:620774803:245146981">
<uiPosition x="718" y="152"/>
</node>
<node npcId="1879395401" tooltip="key:620774803:4412709">
<uiPosition x="1061" y="861"/>
</node>
<node npcId="1879216502" tooltip="key:620774803:126413253">
<uiPosition x="661" y="655"/>
</node>
<node npcId="1879475323" tooltip="key:620774803:51749109">
<uiPosition x="614" y="1145"/>
</node>
<node npcId="1879423250" tooltip="key:620774803:36815909">
<uiPosition x="728" y="116"/>
</node>
<node npcId="1879395876" tooltip="key:620774803:223617541">
<uiPosition x="1102" y="799"/>
</node>
<node npcId="1879231693" tooltip="key:620774803:199733925">
<uiPosition x="797" y="546"/>
</node>
<node npcId="1879475351" tooltip="key:620774803:195140277">
<uiPosition x="631" y="1168"/>
</node>
<node npcId="1879423251" tooltip="key:620774803:36959349">
<uiPosition x="722" y="92"/>
</node>
<node npcId="1879395887" tooltip="key:620774803:241424437">
<uiPosition x="1130" y="770"/>
</node>
<node npcId="1879231696" tooltip="key:620774803:84390069">
<uiPosition x="818" y="530"/>
</node>
<node npcId="1879475331" tooltip="key:620774803:198678133">
<uiPosition x="654" y="1181"/>
</node>
<node npcId="1879395845" tooltip="key:620774803:162659141">
<uiPosition x="1070" y="779"/>
</node>
<node npcId="1879231692" capital="true" tooltip="key:620774803:2219397">
<uiPosition x="819" y="546"/>
</node>
<node npcId="1879493581" tooltip="key:620774803:139093685">
<uiPosition x="858" y="1202"/>
</node>
<node npcId="1879476322" tooltip="key:620774803:30827429">
<uiPosition x="691" y="1186"/>
</node>
<node npcId="1879395861" tooltip="key:620774803:94119509">
<uiPosition x="1092" y="755"/>
</node>
<node npcId="1879231697" tooltip="key:620774803:170259045">
<uiPosition x="841" y="552"/>
</node>
<node npcId="1879493587" tooltip="key:620774803:135785221">
<uiPosition x="868" y="1217"/>
</node>
<node npcId="1879476320" tooltip="key:620774803:207233045">
<uiPosition x="677" y="1242"/>
</node>
<node npcId="1879231695" tooltip="key:620774803:31250101">
<uiPosition x="862" y="564"/>
</node>
<node npcId="1879493579" tooltip="key:620774803:85070709">
<uiPosition x="843" y="1212"/>
</node>
<node npcId="1879476318" tooltip="key:620774803:145940789">
<uiPosition x="720" y="1208"/>
</node>
<node npcId="1879231694" tooltip="key:620774803:22635957">
<uiPosition x="873" y="574"/>
</node>
<node npcId="1879493588" tooltip="key:620774803:141630181">
<uiPosition x="832" y="1243"/>
</node>
<node npcId="1879305978" tooltip="key:620774803:151051013">
<uiPosition x="696" y="643"/>
</node>
<node npcId="1879493580" tooltip="key:620774803:163252853">
<uiPosition x="855" y="1248"/>
</node>
<node npcId="1879485472" tooltip="key:620774803:158322965">
<uiPosition x="781" y="1218"/>
</node>
<node npcId="1879470796" tooltip="key:620774803:120240469">
<uiPosition x="724" y="872"/>
</node>
<node npcId="1879289910" tooltip="key:620906214:141198917">
<uiPosition x="740" y="646"/>
</node>
<node npcId="1879493589" tooltip="key:620774803:202633109">
<uiPosition x="877" y="1253"/>
</node>
<node npcId="1879485463" tooltip="key:620774803:138480645">
<uiPosition x="673" y="980"/>
</node>
<node npcId="1879289923" tooltip="key:620906214:127161941">
<uiPosition x="754" y="665"/>
</node>
<node npcId="1879493583" tooltip="key:620774803:199455653">
<uiPosition x="905" y="1260"/>
</node>
<node npcId="1879485462" tooltip="key:620774803:148546693">
<uiPosition x="666" y="995"/>
</node>
<node npcId="1879470744" tooltip="key:620774803:266123637">
<uiPosition x="673" y="879"/>
</node>
<node npcId="1879289912" tooltip="key:620906214:174111045">
<uiPosition x="723" y="675"/>
</node>
<node npcId="1879485466" tooltip="key:620774803:11223621">
<uiPosition x="687" y="993"/>
</node>
<node npcId="1879470739" tooltip="key:620774803:183324789">
<uiPosition x="703" y="827"/>
</node>
<node npcId="1879289931" capital="true" tooltip="key:620906214:212395381">
<uiPosition x="700" y="728"/>
</node>
<node npcId="1879485967" tooltip="key:620774803:107494773">
<uiPosition x="706" y="985"/>
</node>
<node npcId="1879470666" tooltip="key:620774803:47315685">
<uiPosition x="649" y="822"/>
</node>
<node npcId="1879289932" tooltip="key:620906214:115932581">
<uiPosition x="730" y="715"/>
</node>
<node npcId="1879493590" tooltip="key:620774803:123904821">
<uiPosition x="919" y="1219"/>
</node>
<node npcId="1879485461" tooltip="key:620774803:215921605">
<uiPosition x="675" y="1012"/>
</node>
<node npcId="1879470767" tooltip="key:620774803:57212005">
<uiPosition x="322" y="1197"/>
</node>
<node npcId="1879289905" tooltip="key:620906214:70477877">
<uiPosition x="774" y="674"/>
</node>
<node npcId="1879493582" tooltip="key:620774803:218834725">
<uiPosition x="915" y="1195"/>
</node>
<node npcId="1879485721" tooltip="key:620774803:163254325">
<uiPosition x="688" y="1019"/>
</node>
<node npcId="1879474437" tooltip="key:620774803:186435141">
<uiPosition x="318" y="1177"/>
</node>
<node npcId="1879122756" tooltip="key:620774803:199683829">
<uiPosition x="632" y="516"/>
</node>
<node npcId="1879289914" tooltip="key:620906214:28240357">
<uiPosition x="785" y="654"/>
</node>
<node npcId="1879493591" tooltip="key:620774803:153722133">
<uiPosition x="946" y="1190"/>
</node>
<node npcId="1879485966" tooltip="key:620774803:189685173">
<uiPosition x="724" y="1012"/>
</node>
<node npcId="1879470765" tooltip="key:620774803:210292981">
<uiPosition x="700" y="864"/>
</node>
<node npcId="1879289916" tooltip="key:620906214:111091493">
<uiPosition x="795" y="642"/>
</node>
<node npcId="1879493584" tooltip="key:620774803:41470405">
<uiPosition x="959" y="1220"/>
</node>
<node npcId="1879485465" tooltip="key:620774803:267159797">
<uiPosition x="690" y="1033"/>
</node>
<node npcId="1879470800" tooltip="key:620774803:35797621">
<uiPosition x="685" y="799"/>
</node>
<node npcId="1879289918" capital="true" tooltip="key:620906214:187283893">
<uiPosition x="769" y="705"/>
</node>
<node npcId="1879485467" tooltip="key:620774803:266877093">
<uiPosition x="698" y="1057"/>
</node>
<node npcId="1879474443" tooltip="key:620774803:35359093">
<uiPosition x="248" y="1150"/>
</node>
<node npcId="1879289924" tooltip="key:620906214:57895797">
<uiPosition x="806" y="691"/>
</node>
<node npcId="1879493585" tooltip="key:620774803:241870533">
<uiPosition x="931" y="1267"/>
</node>
<node npcId="1879485464" tooltip="key:620774803:169023013">
<uiPosition x="683" y="1081"/>
</node>
<node npcId="1879470687" tooltip="key:620774803:13559845">
<uiPosition x="226" y="1155"/>
</node>
<node npcId="1879289911" tooltip="key:620906214:176426997">
<uiPosition x="773" y="736"/>
</node>
<node npcId="1879493586" tooltip="key:620774803:219786533">
<uiPosition x="933" y="1233"/>
</node>
<node npcId="1879485719" tooltip="key:620774803:232030597">
<uiPosition x="655" y="1071"/>
</node>
<node npcId="1879289930" capital="true" tooltip="key:620906214:22446021">
<uiPosition x="821" y="764"/>
</node>
<node npcId="1879289920" tooltip="key:620906214:82738469">
<uiPosition x="845" y="735"/>
</node>
<node npcId="1879289925" tooltip="key:620906214:62919029">
<uiPosition x="847" y="763"/>
</node>
<node npcId="1879268515" tooltip="key:620906214:4744229">
<uiPosition x="788" y="591"/>
</node>
<node npcId="1879268518" tooltip="key:620906214:87402645">
<uiPosition x="841" y="586"/>
</node>
<node npcId="1879268516" tooltip="key:620906214:267861173">
<uiPosition x="800" y="605"/>
</node>
<node npcId="1879236981" tooltip="key:620906214:50025141">
<uiPosition x="795" y="624"/>
</node>
<node npcId="1879476317" capital="true" tooltip="key:620774803:204384485">
<uiPosition x="757" y="1210"/>
</node>
<node npcId="1879268517" tooltip="key:620906214:111331829">
<uiPosition x="833" y="611"/>
</node>
<node npcId="1879236983" tooltip="key:620906214:33539061">
<uiPosition x="873" y="610"/>
</node>
<node npcId="1879236982" tooltip="key:620906214:102003813">
<uiPosition x="854" y="631"/>
</node>
<node npcId="1879236811" tooltip="key:620906214:104219381">
<uiPosition x="821" y="648"/>
</node>
<node npcId="1879236985" tooltip="key:620906214:215991365">
<uiPosition x="887" y="640"/>
</node>
<node npcId="1879236976" tooltip="key:620906214:183706709">
<uiPosition x="869" y="655"/>
</node>
<node npcId="1879236986" tooltip="key:620906214:206959509">
<uiPosition x="824" y="682"/>
</node>
<node npcId="1879236979" capital="true" tooltip="key:620906214:198010181">
<uiPosition x="822" y="708"/>
</node>
<node npcId="1879236978" tooltip="key:620906214:115955301">
<uiPosition x="848" y="679"/>
</node>
<node npcId="1879236987" tooltip="key:620906214:199155685">
<uiPosition x="878" y="671"/>
</node>
<node npcId="1879247116" tooltip="key:620906214:17843461">
<uiPosition x="858" y="692"/>
</node>
<node npcId="1879236980" tooltip="key:620906214:21500661">
<uiPosition x="887" y="700"/>
</node>
<node npcId="1879236977" tooltip="key:620906214:53583989">
<uiPosition x="863" y="712"/>
</node>
<node npcId="1879313206" tooltip="key:620774803:255854917">
<uiPosition x="752" y="809"/>
</node>
<node npcId="1879497567" tooltip="key:620774803:76276261">
<uiPosition x="1074" y="454"/>
</node>
<node npcId="1879313224" capital="true" tooltip="key:620774803:80899749">
<uiPosition x="736" y="908"/>
</node>
<node npcId="1879497457" tooltip="key:620774803:165107365">
<uiPosition x="1043" y="496"/>
</node>
<node npcId="1879461296" tooltip="key:620774803:228497941">
<uiPosition x="451" y="1162"/>
</node>
<node npcId="1879313176" tooltip="key:620774803:63946725">
<uiPosition x="810" y="873"/>
</node>
<node npcId="1879497476" tooltip="key:620774803:65722373">
<uiPosition x="1075" y="517"/>
</node>
<node npcId="1879461297" tooltip="key:620774803:89453877">
<uiPosition x="442" y="1135"/>
</node>
<node npcId="1879378805" tooltip="key:620774803:75872437">
<uiPosition x="940" y="153"/>
</node>
<node npcId="1879313210" tooltip="key:620774803:179218037">
<uiPosition x="773" y="903"/>
</node>
<node npcId="1879497672" tooltip="key:620774803:48053861">
<uiPosition x="1114" y="461"/>
</node>
<node npcId="1879461294" tooltip="key:620774803:228331541">
<uiPosition x="442" y="1179"/>
</node>
<node npcId="1879378806" tooltip="key:620774803:261901093">
<uiPosition x="984" y="161"/>
</node>
<node npcId="1879316065" tooltip="key:620774803:200238373">
<uiPosition x="835" y="897"/>
</node>
<node npcId="1879497572" tooltip="key:620774803:117585525">
<uiPosition x="1133" y="444"/>
</node>
<node npcId="1879461292" tooltip="key:620774803:114187749">
<uiPosition x="429" y="1169"/>
</node>
<node npcId="1879378808" tooltip="key:620774803:63620437">
<uiPosition x="1132" y="165"/>
</node>
<node npcId="1879316067" tooltip="key:620774803:9297669">
<uiPosition x="847" y="935"/>
</node>
<node npcId="1879497675" tooltip="key:620774803:117159781">
<uiPosition x="1125" y="474"/>
</node>
<node npcId="1879461293" tooltip="key:620774803:213067637">
<uiPosition x="420" y="1141"/>
</node>
<node npcId="1879378809" tooltip="key:620774803:117208821">
<uiPosition x="1180" y="187"/>
</node>
<node npcId="1879323030" tooltip="key:620774803:65387077">
<uiPosition x="881" y="922"/>
</node>
<node npcId="1879497293" tooltip="key:620774803:145685733">
<uiPosition x="1157" y="510"/>
</node>
<node npcId="1879461291" capital="true" tooltip="key:620774803:110924405">
<uiPosition x="410" y="1189"/>
</node>
<node npcId="1879378807" tooltip="key:620774803:52130581">
<uiPosition x="1118" y="217"/>
</node>
<node npcId="1879316066" tooltip="key:620774803:196964693">
<uiPosition x="902" y="946"/>
</node>
<node npcId="1879461290" tooltip="key:620774803:48927253">
<uiPosition x="409" y="1173"/>
</node>
<node npcId="1879322844" tooltip="key:620774803:186313445">
<uiPosition x="918" y="945"/>
</node>
<node npcId="1879461289" tooltip="key:620774803:188211029">
<uiPosition x="401" y="1158"/>
</node>
<node npcId="1879322843" tooltip="key:620774803:149172181">
<uiPosition x="930" y="934"/>
</node>
<node npcId="1879461288" tooltip="key:620774803:143204597">
<uiPosition x="394" y="1136"/>
</node>
<node npcId="1879322842" tooltip="key:620774803:264711269">
<uiPosition x="956" y="913"/>
</node>
<node npcId="1879461286" tooltip="key:620774803:265193909">
<uiPosition x="380" y="1163"/>
</node>
<node npcId="1879322845" tooltip="key:620774803:172220133">
<uiPosition x="1004" y="895"/>
</node>
<node npcId="1879461285" tooltip="key:620774803:92043653">
<uiPosition x="368" y="1194"/>
</node>
<node npcId="1879322846" tooltip="key:620774803:245239813">
<uiPosition x="1038" y="861"/>
</node>
<node npcId="1879461284" tooltip="key:620774803:262970565">
<uiPosition x="361" y="1174"/>
</node>
<node npcId="1879329077" capital="true" tooltip="key:620774803:2107109">
<uiPosition x="995" y="863"/>
</node>
<node npcId="1879461283" tooltip="key:620774803:69765877">
<uiPosition x="339" y="1178"/>
</node>
<node npcId="1879330248" tooltip="key:620774803:253397813">
<uiPosition x="988" y="879"/>
</node>
<node npcId="1879461298" tooltip="key:620774803:19955733">
<uiPosition x="458" y="1148"/>
</node>
<node npcId="1879330247" tooltip="key:620774803:690981">
<uiPosition x="988" y="849"/>
</node>
<node npcId="1879387154" tooltip="key:620774803:166658181">
<uiPosition x="850" y="275"/>
</node>
<node npcId="1879330246" tooltip="key:620774803:268077877">
<uiPosition x="974" y="877"/>
</node>
<node npcId="1879387156" tooltip="key:620774803:143441029">
<uiPosition x="872" y="422"/>
</node>
<node npcId="1879330250" tooltip="key:620774803:267029301">
<uiPosition x="974" y="851"/>
</node>
<node npcId="1879387157" tooltip="key:620774803:243873893">
<uiPosition x="832" y="461"/>
</node>
<node npcId="1879330249" tooltip="key:620774803:265980725">
<uiPosition x="967" y="864"/>
</node>
<node npcId="1879387160" capital="true" tooltip="key:620774803:35082709">
<uiPosition x="873" y="349"/>
</node>
<node npcId="1879329078" tooltip="key:620774803:117281989">
<uiPosition x="985" y="832"/>
</node>
<node npcId="1879387158" tooltip="key:620774803:158927221">
<uiPosition x="830" y="325"/>
</node>
<node npcId="1879332703" tooltip="key:620774803:46128789">
<uiPosition x="993" y="812"/>
</node>
<node npcId="1879332702" tooltip="key:620774803:58650277">
<uiPosition x="901" y="781"/>
</node>
<node npcId="1879332704" tooltip="key:620774803:183844517">
<uiPosition x="930" y="773"/>
</node>
<node npcId="1879063404" tooltip="key:620774803:159911269">
<uiPosition x="362" y="410"/>
</node>
<node npcId="1879063407" capital="true" tooltip="key:620774803:259602853">
<uiPosition x="356" y="436"/>
</node>
<node npcId="1879063427" tooltip="key:620774803:142169253">
<uiPosition x="381" y="420"/>
</node>
<node npcId="1879063453" tooltip="key:620774803:146884069">
<uiPosition x="399" y="400"/>
</node>
<node npcId="1879357172" tooltip="key:620774803:78804869">
<uiPosition x="1032" y="707"/>
</node>
<node npcId="1879063466" tooltip="key:620774803:12070389">
<uiPosition x="409" y="423"/>
</node>
<node npcId="1879183043" tooltip="key:620774803:263758325">
<uiPosition x="691" y="389"/>
</node>
<node npcId="1879080429" tooltip="key:620774803:139191573">
<uiPosition x="713" y="386"/>
</node>
<node npcId="1879305975" tooltip="key:620774803:205041941">
<uiPosition x="727" y="377"/>
</node>
<node npcId="1879183044" tooltip="key:620774803:233641552">
<uiPosition x="740" y="387"/>
</node>
<node npcId="1879405727" tooltip="key:620774803:2469493">
<uiPosition x="842" y="235"/>
</node>
<node npcId="1879405730" tooltip="key:620774803:92561669">
<uiPosition x="824" y="207"/>
</node>
<node npcId="1879357180" tooltip="key:620774803:84044613">
<uiPosition x="1069" y="749"/>
</node>
<node npcId="1879405728" tooltip="key:620774803:135007605">
<uiPosition x="822" y="193"/>
</node>
<node npcId="1879357190" tooltip="key:620774803:173433621">
<uiPosition x="1088" y="775"/>
</node>
<node npcId="1879405729" tooltip="key:620774803:253683205">
<uiPosition x="790" y="209"/>
</node>
<node npcId="1879357198" tooltip="key:620774803:260368389">
<uiPosition x="1100" y="817"/>
</node>
<node npcId="1879357212" tooltip="key:620774803:199696677">
<uiPosition x="1180" y="823"/>
</node>
<node npcId="1879450374" tooltip="key:620774803:231339365">
<uiPosition x="559" y="558"/>
</node>
<node npcId="1879109765" tooltip="key:620774803:46797941">
<uiPosition x="380" y="182"/>
</node>
<node npcId="1879186735" tooltip="key:620774803:106855525">
<uiPosition x="601" y="568"/>
</node>
<node npcId="1879450376" tooltip="key:620774803:47001285">
<uiPosition x="586" y="559"/>
</node>
<node npcId="1879109766" tooltip="key:620774803:196348197">
<uiPosition x="345" y="229"/>
</node>
<node npcId="1879186737" tooltip="key:620774803:136746981">
<uiPosition x="655" y="591"/>
</node>
<node npcId="1879450378" tooltip="key:620774803:17393525">
<uiPosition x="607" y="544"/>
</node>
<node npcId="1879109764" tooltip="key:620774803:196570405">
<uiPosition x="386" y="224"/>
</node>
<node npcId="1879450379" tooltip="key:620774803:33558101">
<uiPosition x="625" y="553"/>
</node>
<node npcId="1879109762" tooltip="key:620774803:11381605">
<uiPosition x="321" y="189"/>
</node>
<node npcId="1879450377" tooltip="key:620774803:18434837">
<uiPosition x="579" y="521"/>
</node>
<node npcId="1879109763" tooltip="key:620774803:43587109">
<uiPosition x="443" y="263"/>
</node>
<node npcId="1879450380" tooltip="key:620774803:164194853">
<uiPosition x="620" y="541"/>
</node>
<node npcId="1879388246" tooltip="key:620774803:148344533">
<uiPosition x="785" y="418"/>
</node>
<node npcId="1879063338" capital="true" tooltip="key:620774803:84009749">
<uiPosition x="221" y="343"/>
</node>
<node npcId="1879450381" tooltip="key:620774803:156357461">
<uiPosition x="614" y="487"/>
</node>
<node npcId="1879388252" tooltip="key:620774803:148192901">
<uiPosition x="780" y="400"/>
</node>
<node npcId="1879151398" tooltip="key:620774803:124860213">
<uiPosition x="244" y="364"/>
</node>
<node npcId="1879450372" tooltip="key:620774803:230601077">
<uiPosition x="514" y="546"/>
</node>
<node npcId="1879063366" tooltip="key:620774803:226074117">
<uiPosition x="262" y="370"/>
</node>
<node npcId="1879450369" tooltip="key:620774803:192625461">
<uiPosition x="494" y="503"/>
</node>
<node npcId="1879152228" tooltip="key:620774803:91262773">
<uiPosition x="276" y="373"/>
</node>
<node npcId="1879450373" tooltip="key:620774803:170778565">
<uiPosition x="534" y="493"/>
</node>
<node npcId="1879063388" tooltip="key:620774803:238336021">
<uiPosition x="283" y="387"/>
</node>
<node npcId="1879450375" tooltip="key:620774803:15782821">
<uiPosition x="553" y="474"/>
</node>
<node npcId="1879063391" tooltip="key:620774803:101908981">
<uiPosition x="293" y="399"/>
</node>
<node npcId="1879450370" tooltip="key:620774803:28299605">
<uiPosition x="424" y="508"/>
</node>
<node npcId="1879450371" tooltip="key:620774803:54034805">
<uiPosition x="464" y="459"/>
</node>
<node npcId="1879407868" tooltip="key:620774803:224266309">
<uiPosition x="1004" y="878"/>
</node>
<node npcId="1879444655" tooltip="key:620774803:142087717">
<uiPosition x="604" y="424"/>
</node>
<node npcId="1879444650" tooltip="key:620774803:133580405">
<uiPosition x="620" y="432"/>
</node>
<node npcId="1879444654" tooltip="key:620774803:17720821">
<uiPosition x="638" y="424"/>
</node>
<node npcId="1879444664" tooltip="key:620774803:17733029">
<uiPosition x="640" y="442"/>
</node>
<node npcId="1879444657" tooltip="key:620774803:214149221">
<uiPosition x="664" y="432"/>
</node>
<node npcId="1879444662" capital="true" tooltip="key:620774803:235763653">
<uiPosition x="682" y="412"/>
</node>
<node npcId="1879088154" tooltip="key:620774803:218834261">
<uiPosition x="411" y="304"/>
</node>
<node npcId="1879444660" tooltip="key:620774803:149500053">
<uiPosition x="698" y="412"/>
</node>
<node npcId="1879088153" capital="true" tooltip="key:620774803:88843141">
<uiPosition x="400" y="321"/>
</node>
<node npcId="1879444652" tooltip="key:620774803:95068533">
<uiPosition x="604" y="450"/>
</node>
<node npcId="1879109719" tooltip="key:620774803:218892512">
<uiPosition x="384" y="358"/>
</node>
<node npcId="1879444658" tooltip="key:620774803:95047973">
<uiPosition x="598" y="470"/>
</node>
<node npcId="1879204168" tooltip="key:620774803:76552741">
<uiPosition x="417" y="338"/>
</node>
<node npcId="1879444656" tooltip="key:620774803:125359781">
<uiPosition x="624" y="456"/>
</node>
<node npcId="1879204169" tooltip="key:620774803:184532453">
<uiPosition x="415" y="362"/>
</node>
<node npcId="1879088152" tooltip="key:620774803:149175925">
<uiPosition x="395" y="384"/>
</node>
<node npcId="1879063551" tooltip="key:620774803:176117205">
<uiPosition x="467" y="330"/>
</node>
<node npcId="1879063538" tooltip="key:620774803:77565333">
<uiPosition x="463" y="353"/>
</node>
<node npcId="1879063642" tooltip="key:620774803:226837941">
<uiPosition x="499" y="307"/>
</node>
<node npcId="1879183015" tooltip="key:620774803:155730629">
<uiPosition x="502" y="336"/>
</node>
<node npcId="1879063654" capital="true" tooltip="key:620774803:165175797">
<uiPosition x="514" y="318"/>
</node>
<node npcId="1879366394" tooltip="key:620774803:107493573">
<uiPosition x="900" y="257"/>
</node>
<node npcId="1879063672" tooltip="key:620774803:131221029">
<uiPosition x="524" y="273"/>
</node>
<node npcId="1879366395" tooltip="key:620774803:181224085">
<uiPosition x="968" y="213"/>
</node>
<node npcId="1879103913" tooltip="key:620774803:146867008">
<uiPosition x="587" y="226"/>
</node>
<node npcId="1879366396" tooltip="key:620774803:78656901">
<uiPosition x="1040" y="219"/>
</node>
<node npcId="1879103932" tooltip="key:620774803:238505616">
<uiPosition x="585" y="288"/>
</node>
<node npcId="1879366397" capital="true" tooltip="key:620774803:254575253">
<uiPosition x="1052" y="207"/>
</node>
<node npcId="1879325670" tooltip="key:620774803:135567040">
<uiPosition x="646" y="236"/>
</node>
<node npcId="1879366398" tooltip="key:620774803:247734901">
<uiPosition x="1060" y="193"/>
</node>
<node npcId="1879063481" tooltip="key:620774803:157696741">
<uiPosition x="426" y="420"/>
</node>
<node npcId="1879409984" tooltip="key:620774803:104963381">
<uiPosition x="820" y="167"/>
</node>
<node npcId="1879162485" tooltip="key:620774803:218949685">
<uiPosition x="445" y="412"/>
</node>
<node npcId="1879409982" tooltip="key:620774803:63858277">
<uiPosition x="788" y="147"/>
</node>
<node npcId="1879162486" tooltip="key:620774803:49343509">
<uiPosition x="468" y="381"/>
</node>
<node npcId="1879409983" tooltip="key:620774803:71443909">
<uiPosition x="804" y="157"/>
</node>
<node npcId="1879063330" capital="true" tooltip="key:620774803:171008229">
<uiPosition x="467" y="411"/>
</node>
<node npcId="1879063328" tooltip="key:620774803:171064549">
<uiPosition x="482" y="424"/>
</node>
<node npcId="1879063595" tooltip="key:620774803:192719989">
<uiPosition x="484" y="414"/>
</node>
<node npcId="1879063659" tooltip="key:620774803:267137205">
<uiPosition x="527" y="422"/>
</node>
<node npcId="1879063713" tooltip="key:620774803:86690645">
<uiPosition x="580" y="420"/>
</node>
<node npcId="1879444659" tooltip="key:620774803:118322709">
<uiPosition x="614" y="410"/>
</node>
<node npcId="1879444653" tooltip="key:620774803:242761733">
<uiPosition x="635" y="408"/>
</node>
<node npcId="1879122729" tooltip="key:620774803:68922037">
<uiPosition x="633" y="468"/>
</node>
<node npcId="1879122786" tooltip="key:620774803:188541317">
<uiPosition x="650" y="485"/>
</node>
<node npcId="1879122797" tooltip="key:620774803:153285045">
<uiPosition x="676" y="505"/>
</node>
<node npcId="1879136985" tooltip="key:620774803:259628357">
<uiPosition x="1035" y="462"/>
</node>
<node npcId="1879134213" tooltip="key:620774803:84184533">
<uiPosition x="1046" y="451"/>
</node>
<node npcId="1879339115" tooltip="key:620774803:132634261">
<uiPosition x="980" y="864"/>
</node>
<node npcId="1879135401" tooltip="key:620774803:95610757">
<uiPosition x="1057" y="436"/>
</node>
<node npcId="1879339114" tooltip="key:620774803:62468037">
<uiPosition x="1008" y="853"/>
</node>
<node npcId="1879234395" tooltip="key:620774803:120129045">
<uiPosition x="1073" y="435"/>
</node>
<node npcId="1879339113" tooltip="key:620774803:152115365">
<uiPosition x="1026" y="843"/>
</node>
<node npcId="1879134302" tooltip="key:620774803:32743365">
<uiPosition x="1050" y="462"/>
</node>
<node npcId="1879339116" tooltip="key:620774803:7699141">
<uiPosition x="1032" y="805"/>
</node>
<node npcId="1879135683" tooltip="key:620774803:103510437">
<uiPosition x="1044" y="480"/>
</node>
<node npcId="1879339117" tooltip="key:620774803:67727429">
<uiPosition x="1010" y="749"/>
</node>
<node npcId="1879137216" tooltip="key:620774803:238791157">
<uiPosition x="1021" y="525"/>
</node>
<node npcId="1879136986" tooltip="key:620774803:148342741">
<uiPosition x="1054" y="509"/>
</node>
<node npcId="1879134218" tooltip="key:620774803:168070613">
<uiPosition x="1091" y="430"/>
</node>
<node npcId="1879234396" tooltip="key:620774803:98339269">
<uiPosition x="1114" y="430"/>
</node>
<node npcId="1879136002" capital="true" tooltip="key:620774803:214712053">
<uiPosition x="1101" y="446"/>
</node>
<node npcId="1879159499" tooltip="key:620774803:101854101">
<uiPosition x="392" y="339"/>
</node>
<node npcId="1879135402" tooltip="key:620774803:95557429">
<uiPosition x="1078" y="496"/>
</node>
<node npcId="1879457639" tooltip="key:620774803:137033429">
<uiPosition x="550" y="220"/>
</node>
<node npcId="1879204180" tooltip="key:620774803:239554821">
<uiPosition x="403" y="352"/>
</node>
<node npcId="1879134324" tooltip="key:620774803:73950501">
<uiPosition x="1088" y="480"/>
</node>
<node npcId="1879204170" tooltip="key:620774803:195426053">
<uiPosition x="370" y="331"/>
</node>
<node npcId="1879135407" tooltip="key:620774803:252401413">
<uiPosition x="1124" y="493"/>
</node>
<node npcId="1879159493" tooltip="key:620774803:243117685">
<uiPosition x="374" y="301"/>
</node>
<node npcId="1879135678" tooltip="key:620774803:259648261">
<uiPosition x="1160" y="460"/>
</node>
<node npcId="1879216274" tooltip="key:620774803:220590581">
<uiPosition x="641" y="680"/>
</node>
<node npcId="1879216496" tooltip="key:620774803:42340901">
<uiPosition x="663" y="673"/>
</node>
<node npcId="1879186734" tooltip="key:620774803:237838965">
<uiPosition x="647" y="546"/>
</node>
<node npcId="1879216504" tooltip="key:620774803:65118885">
<uiPosition x="681" y="679"/>
</node>
<node npcId="1879186865" tooltip="key:620774803:256319045">
<uiPosition x="614" y="583"/>
</node>
<node npcId="1879216506" tooltip="key:620774803:35066453">
<uiPosition x="682" y="660"/>
</node>
</travelsMap>
