<?xml version="1.0" encoding="UTF-8"?><initialGear>
<class key="Beorning">
<item id="1879320047" name="Well-used Shoulders"/>
<item id="1879320048" name="Old Tunic and Waistcoat"/>
<item id="1879320046" name="Simple Bracers"/>
<item id="1879320045" name="Dirtied Work Boots"/>
<item id="1879319957" name="Old Great Axe"/>
</class>
<class key="Brawler">
<item id="1879450910" name="Cracked Battle-gauntlets"/>
<item id="1879426877" name="Worn Fighting Cloak"/>
<item id="1879426874" name="Worn Fighting Boots"/>
<item id="1879426879" name="Worn Fighting Helm"/>
<item id="1879426876" name="Worn Fighting Leggings"/>
<item id="1879426875" name="Worn Fighting Shoulder Pads"/>
<item id="1879426878" name="Worn Fighting Shirt"/>
</class>
<class key="Burglar">
<item id="1879064323" name="Cloth Gloves"/>
<item id="1879064324" name="Padded Shoes"/>
<item id="1879064325" name="Quilted Leggings"/>
<item id="1879064326" name="Quilted Shirt"/>
<item id="1879064059" name="Table Knife"/>
<item id="1879451463" name="Second Best Table Knife"/>
</class>
<class key="Captain">
<item id="1879064134" name="Leather Gauntlets"/>
<item id="1879064135" name="Leather Boots"/>
<item id="1879064136" name="Leather Jacket"/>
<item id="1879064137" name="Leather Leggings"/>
<item id="1879064138" name="Leather Shoulder Pads"/>
<item id="1879451824" name="Old Two-handed Sword"/>
</class>
<class key="Champion">
<item id="1879064056" name="Leather Leggings"/>
<item id="1879064057" name="Leather Jacket"/>
<item id="1879064058" name="Leather Shoes"/>
<item id="1879064059" name="Table Knife"/>
</class>
<class key="Guardian">
<item id="1879064281" name="Quilted Leggings"/>
<item id="1879064282" name="Leather Boots"/>
<item id="1879064283" name="Leather Shirt"/>
<item id="1879064284" name="Leather Shoulder Guards"/>
<item id="1879064285" name="Leather Gauntlets"/>
<item id="1879064139" name="Weak Mace"/>
<item id="1879052016" name="Split Kite Shield"/>
</class>
<class key="Hunter">
<item id="1879064366" name="Cloth Leggings"/>
<item id="1879064367" name="Cloth Waistcoat"/>
<item id="1879064368" name="Padded Shoes"/>
<item id="1879064059" name="Table Knife"/>
<item id="1879064369" name="Fragile Shortbow"/>
<item id="1879064059" name="Table Knife"/>
</class>
<class key="Lore-master">
<item id="1879110097" name="Robe"/>
<item id="1879064241" name="Quilted Leggings"/>
<item id="1879064242" name="Padded Shoes"/>
<item id="1879064243" name="Simple Staff"/>
</class>
<class key="Minstrel">
<item id="1879064183" name="Quilted Shirt"/>
<item id="1879064184" name="Quilted Leggings"/>
<item id="1879064185" name="Padded Shoes"/>
<item id="1879064139" name="Weak Mace"/>
</class>
<class key="Rune-keeper">
<item id="1879138098" name="Cracked Rune-stone"/>
<item id="1879147372" name="Cloth Robe" race="dwarf"/>
<item id="1879147368" name="Cloth Gloves" race="dwarf"/>
<item id="1879147374" name="Padded Shoes" race="dwarf"/>
<item id="1879147373" name="Cloth Robe" race="elf"/>
<item id="1879147369" name="Cloth Gloves" race="elf"/>
<item id="1879147375" name="Padded Shoes" race="elf"/>
<item id="1879147819" name="Threadbare Rune-satchel"/>
<item id="1879064241" name="Quilted Leggings"/>
<item id="1879147373" name="Cloth Robe" race="highelf"/>
<item id="1879147369" name="Cloth Gloves" race="highelf"/>
<item id="1879147375" name="Padded Shoes" race="highelf"/>
<item id="1879147372" name="Cloth Robe" race="stoutaxedwarf"/>
<item id="1879147368" name="Cloth Gloves" race="stoutaxedwarf"/>
<item id="1879147374" name="Padded Shoes" race="stoutaxedwarf"/>
<item id="1879147373" name="Cloth Robe" race="man"/>
<item id="1879147369" name="Cloth Gloves" race="man"/>
<item id="1879147375" name="Padded Shoes" race="man"/>
</class>
<class key="Warden">
<item id="1879137761" name="Leather Leggings"/>
<item id="1879137759" name="Leather Shirt"/>
<item id="1879137760" name="Leather Shoes"/>
<item id="1879138099" name="Cracked Spear"/>
<item id="1879112531" name="Split Wide Shield"/>
<item id="1879353425" name="Rotted Javelin"/>
</class>
</initialGear>
