<?xml version="1.0" encoding="UTF-8"?><labels locale="es">
<label key="10" value="Siena"/>
<label key="11" value="Tierra de siena"/>
<label key="12" value="Negro"/>
<label key="13" value="Blanco"/>
<label key="14" value="Burdeos"/>
<label key="15" value="Gris"/>
<label key="16" value="Naranja"/>
<label key="17" value="Turquesa"/>
<label key="18" value="Único"/>
<label key="19" value="Azul Evendim"/>
<label key="2" value="Violeta"/>
<label key="20" value="Azul océano"/>
<label key="21" value="Verde bosque"/>
<label key="22" value="Azul Ered Luin"/>
<label key="23" value="Púrpura"/>
<label key="24" value="Verde de Rivendel"/>
<label key="25" value="Rosa"/>
<label key="26" value="Carmesí"/>
<label key="27" value="Verde del Montaraz"/>
<label key="28" value="Amarillo"/>
<label key="29" value="Marrón nogal"/>
<label key="3" value="Azul marino"/>
<label key="30" value="Azul acero"/>
<label key="31" value="Púrpura oscuro"/>
<label key="32" value="Lavanda"/>
<label key="33" value="Durazno de la Comarca"/>
<label key="34" value="Verde del Valle de las Cenizas"/>
<label key="35" value="Plata de Moria"/>
<label key="36" value="Azul de Belegaer"/>
<label key="37" value="Oro de Lórien"/>
<label key="38" value="Verde del Toro Bramador"/>
<label key="39" value="Verde de Rohan"/>
<label key="4" value="Índigo"/>
<label key="40" value="Verde musgo oscuro"/>
<label key="41" value="Arcilla oscura"/>
<label key="42" value="Naranja crepuscular"/>
<label key="43" value="Ciruela de la Comarca"/>
<label key="44" value="Hoja caída de Imladris"/>
<label key="45" value="Hoja de otoño"/>
<label key="46" value="Púrpura crepuscular"/>
<label key="5" value="Verde oscuro"/>
<label key="6" value="Verde oliva"/>
<label key="7" value="Oro"/>
<label key="8" value="Oxidado"/>
<label key="9" value="Rojo"/>
</labels>
